LICENSE
MANIFEST.in
README.rst
setup.py
direct/__init__.py
direct/admin.py
direct/forms.py
direct/models.py
direct/tests.py
direct/urls.py
direct/utils.py
direct/views.py
direct/static/direct/direct/img/layout/favicon.png
direct/static/direct/direct/img/layout/videntity-logo.png
direct/static/direct/direct/modern-business/bin/contact_me.php
direct/static/direct/direct/modern-business/css/bootstrap.css
direct/static/direct/direct/modern-business/css/bootstrap.min.css
direct/static/direct/direct/modern-business/css/modern-business.css
direct/static/direct/direct/modern-business/font-awesome-4.1.0/css/font-awesome.css
direct/static/direct/direct/modern-business/font-awesome-4.1.0/css/font-awesome.min.css
direct/static/direct/direct/modern-business/font-awesome-4.1.0/fonts/FontAwesome.otf
direct/static/direct/direct/modern-business/font-awesome-4.1.0/fonts/fontawesome-webfont.eot
direct/static/direct/direct/modern-business/font-awesome-4.1.0/fonts/fontawesome-webfont.svg
direct/static/direct/direct/modern-business/font-awesome-4.1.0/fonts/fontawesome-webfont.ttf
direct/static/direct/direct/modern-business/font-awesome-4.1.0/fonts/fontawesome-webfont.woff
direct/static/direct/direct/modern-business/font-awesome-4.1.0/less/bordered-pulled.less
direct/static/direct/direct/modern-business/font-awesome-4.1.0/less/core.less
direct/static/direct/direct/modern-business/font-awesome-4.1.0/less/fixed-width.less
direct/static/direct/direct/modern-business/font-awesome-4.1.0/less/font-awesome.less
direct/static/direct/direct/modern-business/font-awesome-4.1.0/less/icons.less
direct/static/direct/direct/modern-business/font-awesome-4.1.0/less/larger.less
direct/static/direct/direct/modern-business/font-awesome-4.1.0/less/list.less
direct/static/direct/direct/modern-business/font-awesome-4.1.0/less/mixins.less
direct/static/direct/direct/modern-business/font-awesome-4.1.0/less/path.less
direct/static/direct/direct/modern-business/font-awesome-4.1.0/less/rotated-flipped.less
django_direct.egg-info/PKG-INFO
django_direct.egg-info/SOURCES.txt
django_direct.egg-info/dependency_links.txt
django_direct.egg-info/requires.txt
django_direct.egg-info/top_level.txt
