Metadata-Version: 1.1
Name: django-direct
Version: 0.7.5
Summary: A simple Django application that provides a RESTFul Direct certificate validation API.
Home-page: https://github.com/videntity/django-direct
Author: Alan Viars
Author-email: sales@videntity.com
License: GPLv2
Platform: UNKNOWN
Classifier: Environment :: Web Environment
Classifier: Framework :: Django
Classifier: Intended Audience :: Developers
Classifier: Operating System :: OS Independent
Classifier: Programming Language :: Python
Classifier: Programming Language :: Python :: 2.7
Classifier: Topic :: Internet :: WWW/HTTP
Classifier: Topic :: Internet :: WWW/HTTP :: Dynamic Content
